thesaurus_lib/__init__.py
thesaurus_lib/config.cfg
thesaurus_lib/downloads.py
thesaurus_lib/thesaurus.py
thesaurus_lib/data/__init__.py
thesaurus_lib/data/back_embeds/__init__.py
thesaurus_lib/data/back_tokens/__init__.py
thesaurus_lib/data/back_tokens/ara_tokens.pickle
thesaurus_lib/data/back_tokens/coca_tokens.pickle
thesaurus_lib/data/back_tokens/deu_tokens.pickle
thesaurus_lib/data/back_tokens/fra_tokens.pickle
thesaurus_lib/data/back_tokens/ru_tokens.pickle
thesaurus_lib/data/index_files/__init__.py
thesaurus_lib/data/index_files/index_eng.pickle
thesaurus_lib/data/index_files/index_ru.pickle
thesaurus_lib/data/pretrained_models/__init__.py
thesaurus_lib/data/stopwords/__init__.py
thesaurus_lib/data/stopwords/extended_stopwords_ara.txt
thesaurus_lib/data/stopwords/extended_stopwords_deu.txt
thesaurus_lib/data/stopwords/extended_stopwords_en.txt
thesaurus_lib/data/stopwords/extended_stopwords_fr.txt
thesaurus_lib/data/stopwords/extended_stopwords_ru.txt
thesaurus_lib/data/texts/2017.txt
thesaurus_lib/data/texts/Idiot.txt
thesaurus_lib/data/texts/King.txt
thesaurus_lib/data/texts/__init__.py
thesaurus_lib/data/texts/berlin.txt
thesaurus_lib/data/texts/covid19.txt
thesaurus_lib/data/texts/descartes.txt
thesaurus_lib/data/texts/machine.txt
thesaurus_lib/data/texts/poems.txt
thesaurus_lib/data/texts/shakespeare.txt
thesaurus_lib/data/texts/stockNews.txt
thesaurus_lib-0.1.9.dist-info/LICENSE
thesaurus_lib-0.1.9.dist-info/METADATA
thesaurus_lib-0.1.9.dist-info/WHEEL
thesaurus_lib-0.1.9.dist-info/top_level.txt
thesaurus_lib-0.1.9.dist-info/RECORD
