Metadata-Version: 2.1
Name: thesaurus-lib
Version: 0.1.9
Summary: Implemented thesaurus library using SOM
Author: Karam Shbeb
Author-email: karam.shbeb1@hotmail.com
Keywords: thesaurus,NLP
Classifier: Programming Language :: Python :: 3
Classifier: Operating System :: OS Independent
Classifier: License :: OSI Approved :: MIT License
License-File: LICENSE
Requires-Dist: setuptools
Requires-Dist: importlib-resources
Requires-Dist: gensim
Requires-Dist: numpy
Requires-Dist: tqdm
Requires-Dist: spacy (>=3.0.5)
Requires-Dist: bokeh
Requires-Dist: minisom
Requires-Dist: transformers
Requires-Dist: sentence-transformers
Requires-Dist: wheel
Requires-Dist: pymorphy2
Requires-Dist: configparser
Requires-Dist: wget
